Metadata-Version: 1.0
Name: wdsnd-distributions
Version: 0.1.2
Summary: Binomial and Gaussian distribution objects
Home-page: UNKNOWN
Author: Wouter ten Brink
Author-email: UNKNOWN
License: UNKNOWN
Platform: UNKNOWN
